huaweicloudsdkiec/__init__.py
huaweicloudsdkiec/v1/__init__.py
huaweicloudsdkiec/v1/iec_async_client.py
huaweicloudsdkiec/v1/iec_client.py
huaweicloudsdkiec/v1/model/__init__.py
huaweicloudsdkiec/v1/model/add_nics_request.py
huaweicloudsdkiec/v1/model/add_nics_request_body.py
huaweicloudsdkiec/v1/model/add_nics_response.py
huaweicloudsdkiec/v1/model/allowed_address_pair.py
huaweicloudsdkiec/v1/model/associate_subnet_request.py
huaweicloudsdkiec/v1/model/associate_subnet_request_body.py
huaweicloudsdkiec/v1/model/associate_subnet_response.py
huaweicloudsdkiec/v1/model/attach_vip_bandwidth_request.py
huaweicloudsdkiec/v1/model/attach_vip_bandwidth_request_body.py
huaweicloudsdkiec/v1/model/attach_vip_bandwidth_response.py
huaweicloudsdkiec/v1/model/attachment.py
huaweicloudsdkiec/v1/model/bandwidth.py
huaweicloudsdkiec/v1/model/bandwidth_config.py
huaweicloudsdkiec/v1/model/bandwidth_config_instance.py
huaweicloudsdkiec/v1/model/bandwidth_type_option.py
huaweicloudsdkiec/v1/model/base_id.py
huaweicloudsdkiec/v1/model/batch_reboot.py
huaweicloudsdkiec/v1/model/batch_reboot_instance_request.py
huaweicloudsdkiec/v1/model/batch_reboot_instance_request_body.py
huaweicloudsdkiec/v1/model/batch_reboot_instance_response.py
huaweicloudsdkiec/v1/model/batch_start.py
huaweicloudsdkiec/v1/model/batch_start_instance_request.py
huaweicloudsdkiec/v1/model/batch_start_instance_request_body.py
huaweicloudsdkiec/v1/model/batch_start_instance_response.py
huaweicloudsdkiec/v1/model/batch_stop.py
huaweicloudsdkiec/v1/model/batch_stop_instance_request.py
huaweicloudsdkiec/v1/model/batch_stop_instance_request_body.py
huaweicloudsdkiec/v1/model/batch_stop_instance_response.py
huaweicloudsdkiec/v1/model/change_os_metadata.py
huaweicloudsdkiec/v1/model/change_os_option.py
huaweicloudsdkiec/v1/model/change_os_request.py
huaweicloudsdkiec/v1/model/change_os_response.py
huaweicloudsdkiec/v1/model/cloud_image_region_info.py
huaweicloudsdkiec/v1/model/coverage.py
huaweicloudsdkiec-3.1.184.dist-info/METADATA
huaweicloudsdkiec-3.1.184.dist-info/WHEEL
huaweicloudsdkiec-3.1.184.dist-info/licenses/LICENSE
huaweicloudsdkiec-3.1.184.dist-info/RECORD
